{"name": "Queen's Enrichment Studies Unit", "coords": [44.2287955, -76.4954906], "addr": "195 University Avenue", "images": [{"src": "/images/buildings/queen's-enrichment-studies-unit.jpg", "alt": "Street view of Queen's Enrichment Studies Unit."}], "desc": ["Q", "u", "e", "e", "n", "'", "s", " ", "E", "n", "r", "i", "c", "h", "m", "e", "n", "t", " ", "S", "t", "u", "d", "i", "e", "s", " ", "U", "n", "i", "t"], "desc_src": "", "access": ["This building directory entry is under construction", "\u00a0", "Link to\u00a0195 University Avenue on the Queen's Campus Map", "Link to\u00a0195 University Avenue on Google Maps", "Floor Plans - N/A", "Site Plans - N/A"], "map": "https://goo.gl/maps/tXyEGNM8ZxgQDo6EA"}